<annotation>
	<folder></folder>
	<filename>set01hjimg8517_jpg.rf.183e390627bb0f492e35739c9415901d.jpg</filename>
	<path>set01hjimg8517_jpg.rf.183e390627bb0f492e35739c9415901d.jpg</path>
	<source>
		<database>roboflow.com</database>
	</source>
	<size>
		<width>640</width>
		<height>640</height>
		<depth>3</depth>
	</size>
	<segmented>0</segmented>
	<object>
		<name>helmet</name>
		<pose>Unspecified</pose>
		<truncated>0</truncated>
		<difficult>0</difficult>
		<occluded>0</occluded>
		<bndbox>
			<xmin>1</xmin>
			<xmax>23</xmax>
			<ymin>36</ymin>
			<ymax>97</ymax>
		</bndbox>
	</object>
	<object>
		<name>helmet</name>
		<pose>Unspecified</pose>
		<truncated>0</truncated>
		<difficult>0</difficult>
		<occluded>0</occluded>
		<bndbox>
			<xmin>219</xmin>
			<xmax>288</xmax>
			<ymin>125</ymin>
			<ymax>249</ymax>
		</bndbox>
	</object>
	<object>
		<name>helmet</name>
		<pose>Unspecified</pose>
		<truncated>0</truncated>
		<difficult>0</difficult>
		<occluded>0</occluded>
		<bndbox>
			<xmin>64</xmin>
			<xmax>90</xmax>
			<ymin>1</ymin>
			<ymax>31</ymax>
		</bndbox>
	</object>
	<object>
		<name>helmet</name>
		<pose>Unspecified</pose>
		<truncated>0</truncated>
		<difficult>0</difficult>
		<occluded>0</occluded>
		<bndbox>
			<xmin>465</xmin>
			<xmax>503</xmax>
			<ymin>55</ymin>
			<ymax>116</ymax>
		</bndbox>
	</object>
	<object>
		<name>helmet</name>
		<pose>Unspecified</pose>
		<truncated>0</truncated>
		<difficult>0</difficult>
		<occluded>0</occluded>
		<bndbox>
			<xmin>361</xmin>
			<xmax>403</xmax>
			<ymin>31</ymin>
			<ymax>94</ymax>
		</bndbox>
	</object>
	<object>
		<name>helmet</name>
		<pose>Unspecified</pose>
		<truncated>0</truncated>
		<difficult>0</difficult>
		<occluded>0</occluded>
		<bndbox>
			<xmin>444</xmin>
			<xmax>476</xmax>
			<ymin>4</ymin>
			<ymax>56</ymax>
		</bndbox>
	</object>
	<object>
		<name>helmet</name>
		<pose>Unspecified</pose>
		<truncated>0</truncated>
		<difficult>0</difficult>
		<occluded>0</occluded>
		<bndbox>
			<xmin>155</xmin>
			<xmax>181</xmax>
			<ymin>7</ymin>
			<ymax>47</ymax>
		</bndbox>
	</object>
	<object>
		<name>helmet</name>
		<pose>Unspecified</pose>
		<truncated>0</truncated>
		<difficult>0</difficult>
		<occluded>0</occluded>
		<bndbox>
			<xmin>583</xmin>
			<xmax>606</xmax>
			<ymin>10</ymin>
			<ymax>41</ymax>
		</bndbox>
	</object>
	<object>
		<name>helmet</name>
		<pose>Unspecified</pose>
		<truncated>0</truncated>
		<difficult>0</difficult>
		<occluded>0</occluded>
		<bndbox>
			<xmin>512</xmin>
			<xmax>541</xmax>
			<ymin>46</ymin>
			<ymax>96</ymax>
		</bndbox>
	</object>
	<object>
		<name>helmet</name>
		<pose>Unspecified</pose>
		<truncated>0</truncated>
		<difficult>0</difficult>
		<occluded>0</occluded>
		<bndbox>
			<xmin>116</xmin>
			<xmax>144</xmax>
			<ymin>1</ymin>
			<ymax>36</ymax>
		</bndbox>
	</object>
	<object>
		<name>helmet</name>
		<pose>Unspecified</pose>
		<truncated>0</truncated>
		<difficult>0</difficult>
		<occluded>0</occluded>
		<bndbox>
			<xmin>375</xmin>
			<xmax>445</xmax>
			<ymin>151</ymin>
			<ymax>238</ymax>
		</bndbox>
	</object>
	<metadata>
	</metadata>
</annotation>
